pylcddc/__init__.py
pylcddc/client.py
pylcddc/commands.py
pylcddc/exceptions.py
pylcddc/iothread.py
pylcddc/responses.py
pylcddc/screen.py
pylcddc/widgets.py
pylcddc-0.4.0.dist-info/LICENSE.txt
pylcddc-0.4.0.dist-info/METADATA
pylcddc-0.4.0.dist-info/WHEEL
pylcddc-0.4.0.dist-info/top_level.txt
pylcddc-0.4.0.dist-info/RECORD
