Metadata-Version: 2.1
Name: pylcddc
Version: 0.4.0
Summary: LCDproc LCDd client
Home-page: https://github.com/shenghaoyang/pylcddc
Author: Shenghao Yang
Author-email: me@shenghaoyang.info
License: MIT
Project-URL: Bug Reports, https://github.com/shenghaoyang/pylcddc/issues
Project-URL: Source, https://github.com/shenghaoyang/pylcddc/
Keywords: lcdproc lcdd
Platform: UNKNOWN
Classifier: Development Status :: 4 - Beta
Classifier: Intended Audience :: Developers
Classifier: Topic :: Software Development :: Libraries :: Python Modules
Classifier: License :: OSI Approved :: MIT License
Classifier: Programming Language :: Python :: 3.6
Classifier: Programming Language :: Python :: 3.7
Classifier: Programming Language :: Python :: 3.8
Classifier: Programming Language :: Python :: 3.9
Requires-Python: >=3.6, < 4
